MANIFEST.in
README.txt
setup.py
c2/__init__.py
c2.patch.contentslist.egg-info/PKG-INFO
c2.patch.contentslist.egg-info/SOURCES.txt
c2.patch.contentslist.egg-info/dependency_links.txt
c2.patch.contentslist.egg-info/entry_points.txt
c2.patch.contentslist.egg-info/namespace_packages.txt
c2.patch.contentslist.egg-info/not-zip-safe
c2.patch.contentslist.egg-info/requires.txt
c2.patch.contentslist.egg-info/top_level.txt
c2/patch/__init__.py
c2/patch/contentslist/__init__.py
c2/patch/contentslist/config.py
c2/patch/contentslist/configure.zcml
c2/patch/contentslist/extender.py
c2/patch/contentslist/interfaces.py
c2/patch/contentslist/overrides.zcml
c2/patch/contentslist/tests.py
c2/patch/contentslist/version.txt
c2/patch/contentslist/browser/__init__.py
c2/patch/contentslist/browser/configlet.py
c2/patch/contentslist/browser/configure.zcml
c2/patch/contentslist/browser/folder_contents.pt
c2/patch/contentslist/browser/foldercontents.py
c2/patch/contentslist/browser/overrides.zcml
c2/patch/contentslist/browser/plone3_folder_contents.pt
c2/patch/contentslist/profiles/default/controlpanel.xml
c2/patch/contentslist/profiles/default/metadata.xml
docs/HISTORY.txt
docs/INSTALL.txt
docs/LICENSE.GPL
docs/LICENSE.txt