Metadata-Version: 1.0
Name: c2.patch.contentslist
Version: 1.0b3
Summary: contents tab viewing order change on folder in Plone
Home-page: http://www.cmscom.jp
Author: Manabu TERADA
Author-email: terada@cmscom.jp
License: GPL
Keywords: plone patch contentstab
Platform: UNKNOWN
Classifier: Framework :: Plone
Classifier: Programming Language :: Python
